setup.py
stat_distribs/Binomialdistribution.py
stat_distribs/Gaussiandistribution.py
stat_distribs/Generaldistribution.py
stat_distribs/__init__.py
stat_distribs.egg-info/PKG-INFO
stat_distribs.egg-info/SOURCES.txt
stat_distribs.egg-info/dependency_links.txt
stat_distribs.egg-info/not-zip-safe
stat_distribs.egg-info/top_level.txt