Metadata-Version: 1.0
Name: stat-distribs
Version: 0.1
Summary: Statistical distributions
Home-page: UNKNOWN
Author: Hafiz Adewuyi
Author-email: myemail@example.com
License: UNKNOWN
Platform: UNKNOWN
